CHANGELOG.md
README.md
mitol/__init__.py
mitol/openedx/__init__.py
mitol/openedx/apps.py
mitol/openedx/py.typed
mitol/openedx/settings/__init__.py
mitol/openedx/utils/__init__.py
mitol/openedx/utils/courses.py
mitol_django_openedx-2025.3.17.dist-info/METADATA
mitol_django_openedx-2025.3.17.dist-info/WHEEL
mitol_django_openedx-2025.3.17.dist-info/RECORD
