Metadata-Version: 2.4
Name: mitol-django-openedx
Version: 2025.3.17
Summary: MIT Open Learning django app extensions for edx related utilities
License-Expression: BSD-3-Clause
Requires-Python: >=3.10
Requires-Dist: django-stubs>=1.13.1
Requires-Dist: django>=3.0
Requires-Dist: edx-opaque-keys==2.2.2
